loan_payment_calc/__init__.py
loan_payment_calc/loans.py
loan_payment_calc-0.1.0.dist-info/METADATA
loan_payment_calc-0.1.0.dist-info/WHEEL
loan_payment_calc-0.1.0.dist-info/top_level.txt
loan_payment_calc-0.1.0.dist-info/RECORD
