Metadata-Version: 2.1
Name: loan-payment-calc
Version: 0.1.0
Summary: Loan payment calculator
Home-page: UNKNOWN
Author: Tyler Norlund
Author-email: t_norlund@u.pacific.edu
License: MIT
Keywords: loan
Platform: UNKNOWN
Classifier: Programming Language :: Python :: 3.7
Classifier: License :: OSI Approved :: MIT License
Classifier: Natural Language :: English
